fasttest/__init__.py
fasttest/driver.py
fasttest/fasttest_runner.py
fasttest/project.py
fasttest/version.py
fasttest/common/__init__.py
fasttest/common/check.py
fasttest/common/decorator.py
fasttest/common/dict.py
fasttest/common/log.py
fasttest/common/variable_global.py
fasttest/drivers/__init__.py
fasttest/drivers/driver.py
fasttest/drivers/driver_base_app.py
fasttest/drivers/driver_base_web.py
fasttest/drivers/appium/__init__.py
fasttest/drivers/appium/driver_appium.py
fasttest/drivers/macaca/__init__.py
fasttest/drivers/macaca/driver_macaca.py
fasttest/keywords/__init__.py
fasttest/keywords/keywords.py
fasttest/result/__init__.py
fasttest/result/html_result.py
fasttest/result/test_result.py
fasttest/result/test_runner.py
fasttest/result/resource/css.css
fasttest/result/resource/js.js
fasttest/runner/__init__.py
fasttest/runner/action_analysis.py
fasttest/runner/action_executor_app.py
fasttest/runner/action_executor_base.py
fasttest/runner/action_executor_web.py
fasttest/runner/case_analysis.py
fasttest/runner/run_case.py
fasttest/runner/test_case.py
fasttest/utils/__init__.py
fasttest/utils/devices_utils.py
fasttest/utils/opcv_utils.py
fasttest/utils/server_utils_app.py
fasttest/utils/server_utils_web.py
fasttest/utils/testcast_utils.py
fasttest/utils/yaml_utils.py
fasttest-1.0.1.dist-info/LICENSE
fasttest-1.0.1.dist-info/METADATA
fasttest-1.0.1.dist-info/WHEEL
fasttest-1.0.1.dist-info/entry_points.txt
fasttest-1.0.1.dist-info/top_level.txt
fasttest-1.0.1.dist-info/RECORD
