Metadata-Version: 2.1
Name: fasttest
Version: 1.0.1
Summary: 关键字驱动自动化框架
Home-page: https://github.com/Jodeee/fasttest
Author: IMJIE
Author-email: imjie@outlook.com
License: UNKNOWN
Keywords: macaca,appium,selenium,APP自动化,WEB自动化,关键字驱动
Platform: UNKNOWN
Classifier: Programming Language :: Python :: 3
Classifier: License :: OSI Approved :: MIT License
Requires-Python: >=3.6
Requires-Dist: PyYAML (>=5.1.2)
Requires-Dist: wd (>=1.0.1)
Requires-Dist: selenium
Requires-Dist: colorama
Requires-Dist: opencv-contrib-python (==3.4.2.16)
